[
  {
    "album": "Twin Fantasy",
    "artist": "Car Seat Headrest",
    "year": 2018,
    "genre": ["Indie Rock"],
    "rating": "3.95",
    "cover": "//e.snmc.io/i/300/s/e96016395b43ba1381db4fba6dff6a12/10085703/Car%20Seat%20Headrest%20-%20Twin%20Fantasy%2C%20Cover%20art.jpeg"
  },
  {
    "album": "KIDS SEE GHOSTS",
    "artist": "KIDS SEE GHOSTS",
    "year": 2018,
    "genre": ["Pop Rap", "Experimental Hip Hop"],
    "rating": "3.88",
    "cover": "//e.snmc.io/i/300/s/6b0f886515ceb38c33a3cf4e320b0bdc/7025219/KIDS%20SEE%20GHOSTS%20-%20KIDS%20SEE%20GHOSTS%2C%20Cover%20art.jpeg"
  },
  {
    "album": "Some Rap Songs",
    "artist": "Earl Sweatshirt",
    "year": 2018,
    "genre": ["Abstract Hip Hop", "Experimental Hip Hop", "Drumless"],
    "rating": "3.89",
    "cover": "//e.snmc.io/i/300/s/d1dcb026d0a8c5e49680e7e20fa07a43/9634567/Earl%20Sweatshirt%20-%20Some%20Rap%20Songs%2C%20Cover%20art.jpeg"
  },
  {
    "album": "You Won't Get What You Want",
    "artist": "Daughters",
    "year": 2018,
    "genre": ["Noise Rock", "Industrial Rock"],
    "rating": "3.86",
    "cover": "//e.snmc.io/i/300/s/1cf4cc549598aeef1098399c40045e3e/7574173/Daughters%20-%20You%20Won't%20Get%20What%20You%20Want%2C%20Cover%20art.png"
  },
  {
    "album": "무너지기 (Crumbling)",
    "artist": "Mid-Air Thief",
    "year": 2018,
    "genre": ["Neo-Psychedelia", "Folktronica", "Psychedelic Pop"],
    "rating": "3.90",
    "cover": "//e.snmc.io/i/300/s/88de63824aacd40629ebe9ac78a2fb4c/7573998/%EA%B3%B5%EC%A4%91%EB%8F%84%EB%91%91%20%5BMid-Air%20Thief%5D%20-%20%EB%AC%B4%EB%84%88%EC%A7%80%EA%B8%B0%20(Crumbling)%2C%20Cover%20art.jpeg"
  },
  {
    "album": "Endless",
    "artist": "Frank Ocean",
    "year": 2018,
    "genre": ["Alternative R&amp;B", "Ambient Pop", "Art Pop"],
    "rating": "3.88",
    "cover": "//e.snmc.io/i/300/s/9c552cd057dff4351bf0e7fe996223e0/6946788/Frank%20Ocean%20-%20Endless%2C%20Cover%20art.jpeg"
  },
  {
    "album": "DAYTONA",
    "artist": "Pusha T",
    "year": 2018,
    "genre": ["Hardcore Hip Hop", "Southern Hip Hop"],
    "rating": "3.81",
    "cover": "//e.snmc.io/i/300/s/b96b95e6e30f214ab6eadc915c13107a/8297443/Pusha%20T%20-%20DAYTONA%2C%20Cover%20art.jpeg"
  },
  {
    "album": "Veteran",
    "artist": "JPEGMAFIA",
    "year": 2018,
    "genre": ["Experimental Hip Hop", "Glitch Hop", "Industrial Hip Hop"],
    "rating": "3.78",
    "cover": "//e.snmc.io/i/300/s/991803469ebfd187c15c17cba517b3b1/6831264/JPEGMAFIA%20-%20Veteran%2C%20Cover%20art.png"
  },
  {
    "album": "OIL OF EVERY PEARL'S UN-INSIDES",
    "artist": "SOPHIE",
    "year": 2018,
    "genre": ["Bubblegum Bass", "Deconstructed Club"],
    "rating": "3.79",
    "cover": "//e.snmc.io/i/300/s/b3316d6a1a6874e44f95bb209875e926/7031879/SOPHIE%20-%20OIL%20OF%20EVERY%20PEARL'S%20UN-INSIDES%2C%20Cover%20art.jpeg"
  },
  {
    "album": "TA13OO",
    "artist": "Denzel Curry",
    "year": 2018,
    "genre": ["Southern Hip Hop", "Trap"],
    "rating": "3.77",
    "cover": "//e.snmc.io/i/300/s/5faa39de7512904dae5e4ac8e39220b5/9824509/Denzel%20Curry%20-%20TA13OO%2C%20Cover%20art.jpeg"
  },
  {
    "album": "Time 'n' Place",
    "artist": "Kero Kero Bonito",
    "year": 2018,
    "genre": ["Twee Pop", "Indie Pop"],
    "rating": "3.79",
    "cover": "//e.snmc.io/i/300/s/8b41d908ace078a7b9e80a75f705f2f7/7182970/Kero%20Kero%20Bonito%20-%20Time%20'n'%20Place%2C%20Cover%20art.jpeg"
  },
  {
    "album": "Dead Magic",
    "artist": "Anna von Hausswolff",
    "year": 2018,
    "genre": ["Neoclassical Darkwave"],
    "rating": "3.81",
    "cover": "//e.snmc.io/i/300/s/276a527ad07573ff52d1fd33b2b12e32/9824517/Anna%20von%20Hausswolff%20-%20Dead%20Magic%2C%20Cover%20art.jpeg"
  },
  {
    "album": "2012 - 2017",
    "artist": "Against All Logic",
    "year": 2018,
    "genre": ["Deep House"],
    "rating": "3.78",
    "cover": "//e.snmc.io/i/300/s/f5f1930177cdc7cf9c7867900d11792b/7183010/Against%20All%20Logic%20-%202012%20-%202017%2C%20Cover%20art.jpeg"
  },
  {
    "album": "qp",
    "artist": "Ichiko Aoba",
    "year": 2018,
    "genre": ["Contemporary Folk", "Singer-Songwriter"],
    "rating": "3.82",
    "cover": "//e.snmc.io/i/300/s/1c7e3bed44ac596731d530b5a271505f/9711077/Ichiko%20Aoba%20-%20qp%2C%20Cover%20art.png"
  },
  {
    "album": "Lance",
    "artist": "Niños del Cerro",
    "year": 2018,
    "genre": ["Neo-Psychedelia", "Indie Rock"],
    "rating": "3.81",
    "cover": "//e.snmc.io/i/300/s/a13e3acec912323a7b84bad97cbb4b50/9824538/Ni%C3%B1os%20del%20Cerro%20-%20Lance%2C%20Cover%20art.jpeg"
  },
  {
    "album": "Slide",
    "artist": "George Clanton",
    "year": 2018,
    "genre": ["Chillwave", "Synthpop", "Hypnagogic Pop"],
    "rating": "3.78",
    "cover": "//e.snmc.io/i/300/s/887a4fbbac805299623546a1610b059c/9753257/George%20Clanton%20-%20Slide%2C%20Cover%20art.jpeg"
  },
  {
    "album": "Die Lit",
    "artist": "Playboi Carti",
    "year": 2018,
    "genre": ["Trap", "Southern Hip Hop", "Cloud Rap"],
    "rating": "3.69",
    "cover": "//e.snmc.io/i/300/s/5b3ed65aaa856d0b597c4d38402742fc/7212299/Playboi%20Carti%20-%20Die%20Lit%2C%20Cover%20art.jpeg"
  },
  {
    "album": "Little Dark Age",
    "artist": "MGMT",
    "year": 2018,
    "genre": ["Synthpop", "Neo-Psychedelia", "Psychedelic Pop"],
    "rating": "3.70",
    "cover": "//e.snmc.io/i/300/s/0c3bf7d14a2fdaba175a5151d88190a2/7936446/MGMT%20-%20Little%20Dark%20Age%2C%20Cover%20art.jpeg"
  },
  {
    "album": "Wide Awake",
    "artist": "Parquet Courts",
    "year": 2018,
    "genre": ["Indie Rock", "Art Punk"],
    "rating": "3.74",
    "cover": "//e.snmc.io/i/300/s/268d4b0064a83acf572e876b91bc10cb/7012920/Parquet%20Courts%20-%20Wide%20Awake%2C%20Cover%20art.jpeg"
  },
  {
    "album": "Joy as an Act of Resistance.",
    "artist": "Idles",
    "year": 2018,
    "genre": ["Post-Punk", "Post-Hardcore"],
    "rating": "3.72",
    "cover": "//e.snmc.io/i/300/s/4b599d34eed6648ca8c24daa201e4b85/8917414/Idles%20-%20Joy%20as%20an%20Act%20of%20Resistance_%2C%20Cover%20art.jpeg"
  },
  {
    "album": "Aviary",
    "artist": "Julia Holter",
    "year": 2018,
    "genre": ["Progressive Pop", "Art Pop", "Experimental"],
    "rating": "3.72",
    "cover": "//e.snmc.io/i/300/s/64acba86815c30adbac3d522f864c11b/9824550/Julia%20Holter%20-%20Aviary%2C%20Cover%20art.jpeg"
  },
  {
    "album": "Tana Talk 3",
    "artist": "Benny the Butcher",
    "year": 2018,
    "genre": ["East Coast Hip Hop", "Gangsta Rap", "Hardcore Hip Hop"],
    "rating": "3.75",
    "cover": "//e.snmc.io/i/300/s/58492213171157eacda462fb5fab9143/7245156/Benny%20the%20Butcher%20-%20Tana%20Talk%203%2C%20Cover%20art.jpeg"
  },
  {
    "album": "Year of the Snitch",
    "artist": "Death Grips",
    "year": 2018,
    "genre": ["Experimental Hip Hop", "Abstract Hip Hop"],
    "rating": "3.64",
    "cover": "//e.snmc.io/i/300/s/60fc82ca6eca3b884d5e9b43497d75ba/7040897/Death%20Grips%20-%20Year%20of%20the%20Snitch%2C%20Cover%20art.jpeg"
  },
  {
    "album": "Your Queen Is a Reptile",
    "artist": "Sons of Kemet",
    "year": 2018,
    "genre": ["Afro-Jazz"],
    "rating": "3.72",
    "cover": "https://e.snmc.io/3.0/img/blocked_art/img_blocked_300x300.png"
  },
  {
    "album": "Musas Vol. 2",
    "artist": "Natalia Lafourcade",
    "year": 2018,
    "genre": ["Nueva canción latinoamericana"],
    "rating": "3.73",
    "cover": "//e.snmc.io/i/300/s/bf12b044b9cf600e785fb7606d691990/6849231/Natalia%20Lafourcade%20-%20Musas%20Vol_%202%2C%20Cover%20art.jpeg"
  },
  {
    "album": "7",
    "artist": "Beach House",
    "year": 2018,
    "genre": ["Dream Pop", "Neo-Psychedelia"],
    "rating": "3.67",
    "cover": "//e.snmc.io/i/300/s/a0daef29442cee78b0c0ed315b7c64e5/7574044/Beach%20House%20-%207%2C%20Cover%20art.jpeg"
  },
  {
    "album": "Untitled Album 1",
    "artist": "Atka",
    "year": 2018,
    "genre": ["Grindcore", "Mathcore"],
    "rating": "3.72",
    "cover": "//e.snmc.io/i/300/s/40e84db07df99f2830153a026e9bac8d/7191828/Atka%20-%20Untitled%20Album%201%2C%20Cover%20art.jpeg"
  },
  {
    "album": "春と修羅 (Haru to Shura)",
    "artist": "Haru Nemuri",
    "year": 2018,
    "genre": ["Noise Pop", "J-Rock"],
    "rating": "3.68",
    "cover": "//e.snmc.io/i/300/s/2ed5e657e0aeb518907f023eca886787/6907500/%E6%98%A5%E3%81%AD%E3%82%80%E3%82%8A%20%5BHaru%20Nemuri%5D%20-%20%E6%98%A5%E3%81%A8%E4%BF%AE%E7%BE%85%20(Haru%20to%20Shura)%2C%20Cover%20art.jpeg"
  },
  {
    "album": "Compro",
    "artist": "Skee Mask",
    "year": 2018,
    "genre": ["Breakbeat", "Ambient Techno"],
    "rating": "3.69",
    "cover": "//e.snmc.io/i/300/s/4593856d174892030fce597b635bb918/10085755/Skee%20Mask%20-%20Compro%2C%20Cover%20art.jpeg"
  },
  {
    "album": "Swimming",
    "artist": "Mac Miller",
    "year": 2018,
    "genre": ["Pop Rap", "Alternative R&amp;B"],
    "rating": "3.65",
    "cover": "//e.snmc.io/i/300/s/d4e02342b985f460641a9129b7c47cd8/7927858/Mac%20Miller%20-%20Swimming%2C%20Cover%20art.jpeg"
  },
  {
    "album": "Schmaltz",
    "artist": "Spanish Love Songs",
    "year": 2018,
    "genre": ["Pop Punk", "Emo"],
    "rating": "3.69",
    "cover": "//e.snmc.io/i/300/s/17fbfcee35d4f51ff919175c3930ed8e/10085757/Spanish%20Love%20Songs%20-%20Schmaltz%2C%20Cover%20art.jpeg"
  },
  {
    "album": "Paraffin",
    "artist": "Armand Hammer",
    "year": 2018,
    "genre": ["Abstract Hip Hop", "East Coast Hip Hop", "Hardcore Hip Hop"],
    "rating": "3.68",
    "cover": "//e.snmc.io/i/300/s/1fef45ec0d6e94d259b5b7eec49448ed/10101371/Armand%20Hammer%20-%20Paraffin%2C%20Cover%20art.jpeg"
  },
  {
    "album": "Future Me Hates Me",
    "artist": "The Beths",
    "year": 2018,
    "genre": ["Power Pop", "Indie Rock"],
    "rating": "3.69",
    "cover": "//e.snmc.io/i/300/s/cb78c65a6a6396770d5daa0f596be29b/10320130/The%20Beths%20-%20Future%20Me%20Hates%20Me%2C%20Cover%20art.jpeg"
  },
  {
    "album": "Isolation",
    "artist": "Kali Uchis",
    "year": 2018,
    "genre": ["Neo-Soul", "Contemporary R&amp;B"],
    "rating": "3.65",
    "cover": "//e.snmc.io/i/300/s/1405aef06e72e2ba47a841f0da97ad22/9280001/Kali%20Uchis%20-%20Isolation%2C%20Cover%20art.png"
  },
  {
    "album": "El mal querer",
    "artist": "Rosalía",
    "year": 2018,
    "genre": ["Flamenco Pop", "Flamenco nuevo", "Art Pop"],
    "rating": "3.64",
    "cover": "//e.snmc.io/i/300/s/8ab9e41a93e76523abed77776429f819/7154312/Rosal%C3%ADa%20-%20El%20mal%20querer%2C%20Cover%20art.jpeg"
  },
  {
    "album": "Phanerozoic I: Palaeozoic",
    "artist": "The Ocean Collective",
    "year": 2018,
    "genre": ["Progressive Metal", "Atmospheric Sludge Metal"],
    "rating": "3.68",
    "cover": "//e.snmc.io/i/300/s/787ecf5f22a5f09165dcfe9f2f8bc95d/7224780/The%20Ocean%20Collective%20-%20Phanerozoic%20I%3A%20Palaeozoic%2C%20Cover%20art.jpeg"
  },
  {
    "album": "Death Spells",
    "artist": "Holy Fawn",
    "year": 2018,
    "genre": ["Post-Metal", "Shoegaze"],
    "rating": "3.67",
    "cover": "//e.snmc.io/i/300/s/6e56c2ef3e1a06eeeb311d844357f859/7176761/Holy%20Fawn%20-%20Death%20Spells%2C%20Cover%20art.jpeg"
  },
  {
    "album": "Super Ghostbusters",
    "artist": "Joel",
    "year": 2018,
    "genre": [
      "Musical Comedy", "Sequencer &amp; Tracker", "Musical Parody"
    ],
    "rating": "3.58",
    "cover": "//e.snmc.io/i/300/s/0882ec4ff24c61f464a18e307c29584d/7258627/Joel%20-%20Super%20Ghostbusters%2C%20Cover%20art.png"
  },
  {
    "album": "NTS Session 4",
    "artist": "Autechre",
    "year": 2018,
    "genre": ["Ambient", "Electronic", "Drone"],
    "rating": "3.67",
    "cover": "//e.snmc.io/i/300/s/ad0f2cf5ad89fa7d813c856973101351/10085780/Autechre%20-%20NTS%20Session%204%2C%20Cover%20art.jpeg"
  },
  {
    "album": "...And as We Have Seen the Storm, We Have Embraced the Eye",
    "artist": "Chapel of Disease",
    "year": 2018,
    "genre": ["Heavy Metal", "Death Metal"],
    "rating": "3.66",
    "cover": "//e.snmc.io/i/300/s/7f43c14ef76c7d7fb0896890f0ebc829/7182973/Chapel%20of%20Disease%20-%20___And%20as%20We%20Have%20Seen%20the%20Storm%2C%20We%20Have%20Embraced%20the%20Eye%2C%20Cover%20art.jpeg"
  },
  {
    "album": "Une main lave l'autre",
    "artist": "Alpha Wann",
    "year": 2018,
    "genre": ["French Hip Hop"],
    "rating": "3.62",
    "cover": "//e.snmc.io/i/300/s/7e992bc32d6710c641b69ea6d97b278b/7146202/Alpha%20Wann%20-%20Une%20main%20lave%20l'autre%2C%20Cover%20art.jpeg"
  },
  {
    "album": "Konoyo",
    "artist": "Tim Hecker",
    "year": 2018,
    "genre": ["Ambient", "Electroacoustic", "Drone"],
    "rating": "3.58",
    "cover": "//e.snmc.io/i/300/s/82f062e46d613fc2dbe91f07d15c5636/7091609/Tim%20Hecker%20-%20Konoyo%2C%20Cover%20art.jpeg"
  },
  {
    "album": "A Drop of Light",
    "artist": "All Traps on Earth",
    "year": 2018,
    "genre": ["Progressive Rock"],
    "rating": "3.61",
    "cover": "//e.snmc.io/i/300/s/4d22ee0733d62d02fe61804f4aafa686/7439635/All%20Traps%20on%20Earth%20-%20A%20Drop%20of%20Light%2C%20Cover%20art.jpeg"
  },
  {
    "album": "The Ugly Art",
    "artist": "Machine Girl",
    "year": 2018,
    "genre": ["Digital Hardcore"],
    "rating": "3.58",
    "cover": "//e.snmc.io/i/300/s/746cf6fd087edbbc93d29c13948b2b42/7193605/Machine%20Girl%20-%20The%20Ugly%20Art%2C%20Cover%20art.png"
  },
  {
    "album": "Shed Blood",
    "artist": "rook",
    "year": 2018,
    "genre": ["Post-Industrial", "Art Pop"],
    "rating": "3.60",
    "cover": "//e.snmc.io/i/300/s/631c417fd97f81ad0b1dac27d0570722/10136586/rook%20-%20Shed%20Blood%2C%20Cover%20art.jpeg"
  },
  {
    "album": "Cheer",
    "artist": "Drug Church",
    "year": 2018,
    "genre": ["Post-Hardcore"],
    "rating": "3.61",
    "cover": "//e.snmc.io/i/300/s/227c39cff5794b40acb7cc93d7a324d0/7099189/Drug%20Church%20-%20Cheer%2C%20Cover%20art.jpeg"
  },
  {
    "album": "De oord",
    "artist": "Fluisteraars",
    "year": 2018,
    "genre": ["Atmospheric Black Metal"],
    "rating": "3.62",
    "cover": "//e.snmc.io/i/300/s/d28e2a911dfd50f6704234c6e30f0744/10105039/Fluisteraars%20%2F%20Turia%20-%20De%20oord%2C%20Cover%20art.jpeg"
  },
  {
    "album": "Antología del cante flamenco heterodoxo",
    "artist": "Niño de Elche",
    "year": 2018,
    "genre": ["Avant-Folk", "Flamenco nuevo"],
    "rating": "3.59",
    "cover": "//e.snmc.io/i/300/s/8d330a680f09910bb2654caa3ba90169/6884518/Ni%C3%B1o%20de%20Elche%20-%20Antolog%C3%ADa%20del%20cante%20flamenco%20heterodoxo%2C%20Cover%20art.jpeg"
  },
  {
    "album": "WILKES",
    "artist": "Sam Wilkes",
    "year": 2018,
    "genre": ["Nu Jazz", "Jazz"],
    "rating": "3.62",
    "cover": "//e.snmc.io/i/300/s/0c45b4fcb1426cedd89b296b1e72a2ed/7180594/Sam%20Wilkes%20-%20WILKES%2C%20Cover%20art.jpeg"
  },
  {
    "album": "愛をあるだけ、すべて (Ai wo arudake, subete)",
    "artist": "Kirinji",
    "year": 2018,
    "genre": ["City Pop", "J-Pop"],
    "rating": "3.61",
    "cover": "//e.snmc.io/i/300/s/4d990e745911bded96dfbfb113f899b1/6995220/%E3%82%AD%E3%83%AA%E3%83%B3%E3%82%B8%20%5BKirinji%5D%20-%20%E6%84%9B%E3%82%92%E3%81%82%E3%82%8B%E3%81%A0%E3%81%91%E3%80%81%E3%81%99%E3%81%B9%E3%81%A6%20(Ai%20wo%20arudake%2C%20subete)%2C%20Cover%20art.jpeg"
  },
  {
    "album": "Abysskiss",
    "artist": "Adrianne Lenker",
    "year": 2018,
    "genre": ["Singer-Songwriter", "Indie Folk"],
    "rating": "3.59",
    "cover": "//e.snmc.io/i/300/s/463c44295b3b3b556aca66a5e8fedf4b/7135953/Adrianne%20Lenker%20-%20Abysskiss%2C%20Cover%20art.jpeg"
  },
  {
    "album": "Negro Swan",
    "artist": "Blood Orange",
    "year": 2018,
    "genre": ["Alternative R&amp;B", "Sophisti-Pop"],
    "rating": "3.57",
    "cover": "//e.snmc.io/i/300/s/cbc3e1d1e3d87010036efb77ee4e9b95/7077225/Blood%20Orange%20-%20Negro%20Swan%2C%20Cover%20art.jpeg"
  },
  {
    "album": "From the Gallery of Sleep",
    "artist": "Night Verses",
    "year": 2018,
    "genre": ["Progressive Metal"],
    "rating": "3.60",
    "cover": "//e.snmc.io/i/300/s/81954c358bc8ad6a32908f4b3bfbceea/10102904/Night%20Verses%20-%20From%20the%20Gallery%20of%20Sleep%2C%20Cover%20art.jpeg"
  },
  {
    "album": "Wulkanaz",
    "artist": "Wulkanaz",
    "year": 2018,
    "genre": ["Black Metal"],
    "rating": "3.60",
    "cover": "//e.snmc.io/i/300/s/8eb58420a84f8d700b03e9f95bc81bcf/7298221/Wulkanaz%20-%20Wulkanaz%2C%20Cover%20art.jpeg"
  },
  {
    "album": "Empty Black",
    "artist": "Greyhaven",
    "year": 2018,
    "genre": ["Metalcore", "Post-Hardcore"],
    "rating": "3.61",
    "cover": "//e.snmc.io/i/300/s/a96b8907d20a7e44690a15187b8ae630/6918031/Greyhaven%20-%20Empty%20Black%2C%20Cover%20art.jpeg"
  },
  {
    "album": "Djarimirri: Child of the Rainbow",
    "artist": "Gurrumul",
    "year": 2018,
    "genre": ["Post-Minimalism", "Indigenous Australian Traditional Music"],
    "rating": "3.60",
    "cover": "//e.snmc.io/i/300/s/0aea68358a84203410195aaa01711952/7092358/Gurrumul%20-%20Djarimirri%3A%20Child%20of%20the%20Rainbow%2C%20Cover%20art.jpeg"
  },
  {
    "album": "A Breukelen Story",
    "artist": "Masta Ace",
    "year": 2018,
    "genre": ["East Coast Hip Hop", "Boom Bap"],
    "rating": "3.62",
    "cover": "//e.snmc.io/i/300/s/a20b301002077bb79a8410717471b050/10103562/Masta%20Ace%20%26%20Marco%20Polo%20-%20A%20Breukelen%20Story%2C%20Cover%20art.jpeg"
  },
  {
    "album": "Unfold the God Man",
    "artist": "Psychonaut",
    "year": 2018,
    "genre": ["Progressive Metal"],
    "rating": "3.61",
    "cover": "//e.snmc.io/i/300/s/b8eb4c4d2348a292e788a0fedb46f6f7/10107563/Psychonaut%20-%20Unfold%20the%20God%20Man%2C%20Cover%20art.jpeg"
  },
  {
    "album": "Bark Your Head Off, Dog",
    "artist": "Hop Along",
    "year": 2018,
    "genre": ["Indie Rock"],
    "rating": "3.58",
    "cover": "//e.snmc.io/i/300/s/759ad32e61a689e25544777f989ba692/6839963/Hop%20Along%20-%20Bark%20Your%20Head%20Off%2C%20Dog%2C%20Cover%20art.jpeg"
  },
  {
    "album": "Supreme Blientele",
    "artist": "Westside Gunn",
    "year": 2018,
    "genre": ["East Coast Hip Hop", "Hardcore Hip Hop"],
    "rating": "3.58",
    "cover": "//e.snmc.io/i/300/s/e01aca7c7446c3acc71152b9189245eb/10147480/Westside%20Gunn%20-%20Supreme%20Blientele%2C%20Cover%20art.jpeg"
  },
  {
    "album": "Inhüma",
    "artist": "Esoctrilihum",
    "year": 2018,
    "genre": ["Black Metal", "Death Metal"],
    "rating": "3.59",
    "cover": "//e.snmc.io/i/300/s/12057e6692829cf8179f27360327903b/7238251/Esoctrilihum%20-%20Inh%C3%BCma%2C%20Cover%20art.jpeg"
  },
  {
    "album": "Sentiment",
    "artist": "Un",
    "year": 2018,
    "genre": ["Funeral Doom Metal"],
    "rating": "3.62",
    "cover": "//e.snmc.io/i/300/s/f0128436a1add30d1ca76a555df5b399/7074768/Un%20-%20Sentiment%2C%20Cover%20art.jpeg"
  },
  {
    "album": "Kryptonyte",
    "artist": "Kryptonyte",
    "year": 2018,
    "genre": ["Southern Hip Hop", "Memphis Rap"],
    "rating": "3.60",
    "cover": "//e.snmc.io/i/300/s/541ca19fd6388849ccfce5802fd18d4f/10102883/Kryptonyte%20-%20Kryptonyte%2C%20Cover%20art.jpeg"
  },
  {
    "album": "Firepower",
    "artist": "Judas Priest",
    "year": 2018,
    "genre": ["Heavy Metal"],
    "rating": "3.56",
    "cover": "//e.snmc.io/i/300/s/364c6ac13e3649243988636e892377c6/6763239/Judas%20Priest%20-%20Firepower%2C%20Cover%20art.jpeg"
  },
  {
    "album": "美しい終末サイクル",
    "artist": "Jyocho",
    "year": 2018,
    "genre": ["Math Rock", "Math Pop"],
    "rating": "3.59",
    "cover": "//e.snmc.io/i/300/s/d42af13987cea32e3e513197e3277464/7254077/Jyocho%20-%20%E7%BE%8E%E3%81%97%E3%81%84%E7%B5%82%E6%9C%AB%E3%82%B5%E3%82%A4%E3%82%AF%E3%83%AB%2C%20Cover%20art.jpeg"
  },
  {
    "album": "Limp Pumpo",
    "artist": "Jesus Belluci",
    "year": 2018,
    "genre": ["Ghettotech"],
    "rating": "3.58",
    "cover": "//e.snmc.io/i/300/s/ce77526d2142f7295a2cd2c30ce8988c/8497364/Jesus%20Belluci%20-%20Limp%20Pumpo%2C%20Cover%20art.jpeg"
  },
  {
    "album": "Excursions",
    "artist": "C418",
    "year": 2018,
    "genre": ["Progressive House"],
    "rating": "3.60",
    "cover": "//e.snmc.io/i/300/s/21f8b7c2a01b2006226d6ba34ae4f15a/10102836/C418%20-%20Excursions%2C%20Cover%20art.jpeg"
  },
  {
    "album": "Make Room",
    "artist": "Destroy Boys",
    "year": 2018,
    "genre": ["Punk Rock", "Pop Punk"],
    "rating": "3.60",
    "cover": "//e.snmc.io/i/300/s/33103c84a333a1bf99fcff87f13207c4/9571435/Destroy%20Boys%20-%20Make%20Room%2C%20Cover%20art.jpeg"
  },
  {
    "album": "I Love My Mom",
    "artist": "Indigo De Souza",
    "year": 2018,
    "genre": ["Indie Rock", "Singer-Songwriter"],
    "rating": "3.60",
    "cover": "https://e.snmc.io/3.0/img/blocked_art/img_blocked_300x300.png"
  },
  {
    "album": "Amir",
    "artist": "Tamino",
    "year": 2018,
    "genre": ["Art Pop", "Singer-Songwriter"],
    "rating": "3.59",
    "cover": "//e.snmc.io/i/300/s/64a71e0b03baa8c2877edcde9a10f826/7200397/Tamino%20-%20Amir%2C%20Cover%20art.jpeg"
  },
  {
    "album": "Wolastoqiyik Lintuwakonawa",
    "artist": "Jeremy Dutcher",
    "year": 2018,
    "genre": [
      "Art Pop", "Indigenous North American Music", "Chamber Music"
    ],
    "rating": "3.61",
    "cover": "//e.snmc.io/i/300/s/22b9a464defc8a2d8c2e708eb211145b/10107631/Jeremy%20Dutcher%20-%20Wolastoqiyik%20Lintuwakonawa%2C%20Cover%20art.jpeg"
  },
  {
    "album": "The Incubus of Karma",
    "artist": "Mournful Congregation",
    "year": 2018,
    "genre": ["Funeral Doom Metal"],
    "rating": "3.59",
    "cover": "//e.snmc.io/i/300/s/3b03fcbcc3febc58f46ca8bd4592916a/7160621/Mournful%20Congregation%20-%20The%20Incubus%20of%20Karma%2C%20Cover%20art.jpeg"
  },
  {
    "album": "小圈子",
    "artist": "Understatement",
    "year": 2018,
    "genre": ["Ambient", "Dreampunk"],
    "rating": "3.58",
    "cover": "//e.snmc.io/i/300/s/6bd422050e49f6619e0e921ba3526c5b/10101442/%E8%BC%95%E6%8F%8F%E6%B7%A1%E5%AF%AB%20%5BUnderstatement%5D%20-%20%E5%B0%8F%E5%9C%88%E5%AD%90%2C%20Cover%20art.png"
  },
  {
    "album": "Feast for Water",
    "artist": "Messa",
    "year": 2018,
    "genre": ["Doom Metal"],
    "rating": "3.59",
    "cover": "//e.snmc.io/i/300/s/69487c8522fdeb66b1a3c08c2165bf28/7074961/Messa%20-%20Feast%20for%20Water%2C%20Cover%20art.jpeg"
  },
  {
    "album": "Good to Feel",
    "artist": "Candy",
    "year": 2018,
    "genre": ["Hardcore Punk", "Metalcore"],
    "rating": "3.60",
    "cover": "https://e.snmc.io/3.0/img/blocked_art/img_blocked_300x300.png"
  },
  {
    "album": "Qujaku",
    "artist": "Qujaku",
    "year": 2018,
    "genre": ["Noise Rock", "Experimental Rock"],
    "rating": "3.60",
    "cover": "//e.snmc.io/i/300/s/de21cd5d5d0b68aa83980ce7c386ca8a/7289197/Qujaku%20-%20Qujaku%2C%20Cover%20art.jpeg"
  },
  {
    "album": "Lato w ghettcie",
    "artist": "Ćpaj Stajl",
    "year": 2018,
    "genre": ["Hardcore Hip Hop"],
    "rating": "3.58",
    "cover": "//e.snmc.io/i/300/s/688c06478b15fd78af27f8410332e8c9/7168502/%C4%86paj%20Stajl%20-%20Lato%20w%20ghettcie%2C%20Cover%20art.png"
  },
  {
    "album": "Dhorimviskha",
    "artist": "Koenji Hyakkei",
    "year": 2018,
    "genre": ["Zeuhl"],
    "rating": "3.57",
    "cover": "//e.snmc.io/i/300/s/569518398d8d8717e59b42644c1c732b/7074333/Koenji%20Hyakkei%20-%20Dhorimviskha%2C%20Cover%20art.jpeg"
  },
  {
    "album": "The Scythe of Cosmic Chaos",
    "artist": "Sulphur Aeon",
    "year": 2018,
    "genre": ["Death Metal", "Black Metal"],
    "rating": "3.58",
    "cover": "//e.snmc.io/i/300/s/7c84d25740fb53be06c5fafe63e7ee48/7320506/Sulphur%20Aeon%20-%20The%20Scythe%20of%20Cosmic%20Chaos%2C%20Cover%20art.jpeg"
  },
  {
    "album": "Wasteland",
    "artist": "Riverside",
    "year": 2018,
    "genre": ["Progressive Rock"],
    "rating": "3.57",
    "cover": "//e.snmc.io/i/300/s/273992c64851a3dea9ca94a0271cfbbd/7280612/Riverside%20-%20Wasteland%2C%20Cover%20art.jpeg"
  },
  {
    "album": "A Laughing Death in Meatspace",
    "artist": "Tropical Fuck Storm",
    "year": 2018,
    "genre": ["Art Punk", "Punk Blues", "Noise Rock"],
    "rating": "3.63",
    "cover": "//e.snmc.io/i/300/s/88ede12f1461406e9fdb87c8b31ddd9f/10085765/Tropical%20Fuck%20Storm%20-%20A%20Laughing%20Death%20in%20Meatspace%2C%20Cover%20art.jpeg"
  },
  {
    "album": "Safe in the Hands of Love",
    "artist": "Yves Tumor",
    "year": 2018,
    "genre": ["Neo-Psychedelia", "Post-Industrial", "Art Pop"],
    "rating": "3.61",
    "cover": "//e.snmc.io/i/300/s/3301032bc28de1c189065516bce14f6e/7149991/Yves%20Tumor%20-%20Safe%20in%20the%20Hands%20of%20Love%2C%20Cover%20art.jpeg"
  },
  {
    "album": "NTS Session 3",
    "artist": "Autechre",
    "year": 2018,
    "genre": ["IDM"],
    "rating": "3.65",
    "cover": "//e.snmc.io/i/300/s/8dfd2a13975e8d0cfa3b084bb288582e/10085776/Autechre%20-%20NTS%20Session%203%2C%20Cover%20art.jpeg"
  },
  {
    "album": "Infernal Decadence",
    "artist": "Spectral Wound",
    "year": 2018,
    "genre": ["Black Metal"],
    "rating": "3.66",
    "cover": "//e.snmc.io/i/300/s/a73b613031aa700e37875466c05e5565/6997445/Spectral%20Wound%20-%20Infernal%20Decadence%2C%20Cover%20art.jpeg"
  },
  {
    "album": "Residue",
    "artist": "Blind Girls",
    "year": 2018,
    "genre": ["Emoviolence"],
    "rating": "3.66",
    "cover": "//e.snmc.io/i/300/s/d9ef6675212b70d579b8564a26b2eeaa/9814115/Blind%20Girls%20-%20Residue%2C%20Cover%20art.jpeg"
  },
  {
    "album": "Orpheus vs. the Sirens",
    "artist": "Hermit and the Recluse",
    "year": 2018,
    "genre": ["Abstract Hip Hop", "East Coast Hip Hop", "Drumless"],
    "rating": "3.64",
    "cover": "//e.snmc.io/i/300/s/b0b6c11cc5346563130791d87bddf627/7115502/Hermit%20and%20the%20Recluse%20-%20Orpheus%20vs_%20the%20Sirens%2C%20Cover%20art.jpeg"
  },
  {
    "album": "There Is a Place",
    "artist": "Maisha",
    "year": 2018,
    "genre": ["Spiritual Jazz"],
    "rating": "3.67",
    "cover": "//e.snmc.io/i/300/s/c48555c94f46d873f3a5ee13cddeeba8/7238896/Maisha%20-%20There%20Is%20a%20Place%2C%20Cover%20art.jpeg"
  },
  {
    "album": "Animals Acoustic",
    "artist": "TTNG",
    "year": 2018,
    "genre": ["Acoustic Rock", "Midwest Emo", "Math Pop"],
    "rating": "3.65",
    "cover": "//e.snmc.io/i/300/s/43b44817cf6ed8feaa24720d2e0c261b/10085784/TTNG%20-%20Animals%20Acoustic%2C%20Cover%20art.jpeg"
  },
  {
    "album": "Care for Me",
    "artist": "Saba",
    "year": 2018,
    "genre": ["Conscious Hip Hop", "Jazz Rap"],
    "rating": "3.61",
    "cover": "//e.snmc.io/i/300/s/24a91b0c5b0d4e4d91b02d271ae603a0/6939957/Saba%20-%20Care%20for%20Me%2C%20Cover%20art.jpeg"
  },
  {
    "album": "Double Negative",
    "artist": "Low",
    "year": 2018,
    "genre": ["Ambient Pop", "Glitch Pop"],
    "rating": "3.61",
    "cover": "//e.snmc.io/i/300/s/db8a022e4f61c87394452a4722278dfd/8773071/Low%20-%20Double%20Negative%2C%20Cover%20art.jpeg"
  },
  {
    "album": "Woman Worldwide",
    "artist": "Justice",
    "year": 2018,
    "genre": ["French Electro", "Electro House", "Mashup"],
    "rating": "3.64",
    "cover": "//e.snmc.io/i/300/s/3cd9a1265517ba45388a27009bfd3c49/7041936/Justice%20-%20Woman%20Worldwide%2C%20Cover%20art.jpeg"
  },
  {
    "album": "The Sciences",
    "artist": "Sleep",
    "year": 2018,
    "genre": ["Stoner Metal", "Doom Metal"],
    "rating": "3.61",
    "cover": "//e.snmc.io/i/300/s/32f853759181a33a217f397857e5593d/6958632/Sleep%20-%20The%20Sciences%2C%20Cover%20art.jpeg"
  },
  {
    "album": "Everywhere at the End of Time: Stage 4",
    "artist": "The Caretaker",
    "year": 2018,
    "genre": ["Sound Collage", "Turntable Music", "Dark Ambient"],
    "rating": "3.61",
    "cover": "//e.snmc.io/i/300/s/57af9d4b016a5a60f81ff65aaf44ab63/6940445/The%20Caretaker%20-%20Everywhere%20at%20the%20End%20of%20Time%3A%20Stage%204%2C%20Cover%20art.jpeg"
  },
  {
    "album": "Abandonnée/Maléja",
    "artist": "La Tène &amp; Jacques Puech et Louis Jacques &amp; Jérémie Sauvage et Guilhem Lacroux",
    "year": 2018,
    "genre": ["Drone", "Avant-Folk", "Post-Minimalism"],
    "rating": "3.65",
    "cover": "//e.snmc.io/i/300/s/2329a1089d16f5c1292f5a2ebf5e4417/10085769/La%20T%C3%A8ne%20%26%20Jacques%20Puech%20et%20Louis%20Jacques%20%26%20J%C3%A9r%C3%A9mie%20Sauvage%20et%20Guilhem%20Lacroux%20-%20Abandonn%C3%A9e%2FMal%C3%A9ja%2C%20Cover%20art.jpeg"
  },
  {
    "album": "Surface II Air Missive",
    "artist": "Surface to Air Missive",
    "year": 2018,
    "genre": ["Indie Rock", "Power Pop"],
    "rating": "3.66",
    "cover": "//e.snmc.io/i/300/s/70517f8f010c1f1011cc23c051fb1220/10105188/Surface%20to%20Air%20Missive%20-%20Surface%20II%20Air%20Missive%2C%20Cover%20art.jpeg"
  },
  {
    "album": "Grievous",
    "artist": "Convulsing",
    "year": 2018,
    "genre": ["Black Metal", "Death Metal", "Dissonant Death Metal"],
    "rating": "3.64",
    "cover": "//e.snmc.io/i/300/s/71e0c02e535a8b73dd5027be3a3a4744/10085789/Convulsing%20-%20Grievous%2C%20Cover%20art.jpeg"
  },
  {
    "album": "Room 25",
    "artist": "Noname",
    "year": 2018,
    "genre": ["Jazz Rap", "Conscious Hip Hop"],
    "rating": "3.60",
    "cover": "//e.snmc.io/i/300/s/483caac5e8142cad9f97c5bfbc9f341f/10202590/Noname%20-%20Room%2025%2C%20Cover%20art.jpeg"
  },
  {
    "album": "Avantdale Bowling Club",
    "artist": "Avantdale Bowling Club",
    "year": 2018,
    "genre": ["Jazz Rap", "Conscious Hip Hop"],
    "rating": "3.62",
    "cover": "//e.snmc.io/i/300/s/56ee1b7b9e53e8edae9827a87db0b722/7562802/Avantdale%20Bowling%20Club%20-%20Avantdale%20Bowling%20Club%2C%20Cover%20art.jpeg"
  },
  {
    "album": "In the Future Your Body Will Be the Furthest Thing From Your Mind",
    "artist": "Failure",
    "year": 2018,
    "genre": ["Alternative Rock"],
    "rating": "3.66",
    "cover": "//e.snmc.io/i/300/s/c207c242b85dd23d4733dc11b24217ac/7237923/Failure%20-%20In%20the%20Future%20Your%20Body%20Will%20Be%20the%20Furthest%20Thing%20From%20Your%20Mind%2C%20Cover%20art.jpeg"
  },
  {
    "album": "The Fifty Eleven Project",
    "artist": "Kasper Bjørke Quartet",
    "year": 2018,
    "genre": ["Post-Minimalism", "Ambient"],
    "rating": "3.65",
    "cover": "//e.snmc.io/i/300/s/ce5d4d46c567376d7098f9d936034e55/10085786/Kasper%20Bj%C3%B8rke%20Quartet%20-%20The%20Fifty%20Eleven%20Project%2C%20Cover%20art.jpeg"
  }
]
